vega/AST.py
vega/Exceptions.py
vega/Feature.py
vega/Functions.py
vega/Law.py
vega/Map.py
vega/Model.py
vega/Satisfiability.py
vega/Solver.py
vega/Tactic.py
vega/__init__.py
vega/app.py
vega/helper.py
vega/smtlib/SmtlibCapability.py
vega/smtlib/__init__.py
vega/smtlib/app.py
vega/smtlib/parse.py
vega/smtlib/pysmt/ExtendedSmtLibParser.py
vega/smtlib/pysmt/__init__.py
vega/smtlib/vega/Command.py
vega/smtlib/vega/Fnode.py
vega/smtlib/vega/SymbolType.py
vega/smtlib/vega/VegaSmtLibParser.py
vega/smtlib/vega/__init__.py
vega/smtlib/vega/helper.py
vega_solver-0.1.0.dist-info/LICENSE
vega_solver-0.1.0.dist-info/METADATA
vega_solver-0.1.0.dist-info/WHEEL
vega_solver-0.1.0.dist-info/entry_points.txt
vega_solver-0.1.0.dist-info/top_level.txt
vega_solver-0.1.0.dist-info/RECORD
