Metadata-Version: 2.1
Name: vega-solver
Version: 0.1.0
Summary: All sat style yet another theorem solver
Home-page: https://github.com/K-atc/vega-solver
Author: Tomori Nao (@K_atc)
Author-email: shiftx1026@gmail.com
License: MIT License
Requires-Dist: PySMT
